{
  "table": "listening_ports",
  "query": "select port, protocol, address, pid, socket, path from listening_ports order by port, protocol, pid;",
  "tool": "osqueryi version 4.9.0",
  "vantage": "containerized osquery sharing aptl-shuffle-backend network namespace",
  "status": "captured",
  "rows": [
    {
      "address": "",
      "path": "/run/docker.sock",
      "pid": "-1",
      "port": "0",
      "protocol": "0",
      "socket": "0"
    },
    {
      "address": "",
      "path": "/run/docker.sock",
      "pid": "-1",
      "port": "0",
      "protocol": "0",
      "socket": "0"
    },
    {
      "address": "::",
      "path": "",
      "pid": "1",
      "port": "5001",
      "protocol": "6",
      "socket": "170256223"
    },
    {
      "address": "127.0.0.11",
      "path": "",
      "pid": "-1",
      "port": "34327",
      "protocol": "6",
      "socket": "170244067"
    },
    {
      "address": "127.0.0.11",
      "path": "",
      "pid": "-1",
      "port": "53753",
      "protocol": "17",
      "socket": "170244066"
    }
  ]
}
