{
  "table": "listening_ports",
  "query": "select port, protocol, address, pid, socket, path from listening_ports order by port, protocol, pid;",
  "tool": "osqueryi version 4.9.0",
  "vantage": "containerized osquery sharing aptl-misp-redis network namespace",
  "status": "captured",
  "rows": [
    {
      "address": "0.0.0.0",
      "path": "",
      "pid": "-1",
      "port": "6379",
      "protocol": "6",
      "socket": "170228075"
    },
    {
      "address": "::",
      "path": "",
      "pid": "-1",
      "port": "6379",
      "protocol": "6",
      "socket": "170228076"
    },
    {
      "address": "0.0.0.0",
      "path": "",
      "pid": "-1",
      "port": "6379",
      "protocol": "6",
      "socket": "170228075"
    },
    {
      "address": "::",
      "path": "",
      "pid": "-1",
      "port": "6379",
      "protocol": "6",
      "socket": "170228076"
    },
    {
      "address": "127.0.0.11",
      "path": "",
      "pid": "-1",
      "port": "33479",
      "protocol": "6",
      "socket": "170229800"
    },
    {
      "address": "127.0.0.11",
      "path": "",
      "pid": "-1",
      "port": "33479",
      "protocol": "6",
      "socket": "170229800"
    },
    {
      "address": "127.0.0.11",
      "path": "",
      "pid": "-1",
      "port": "45861",
      "protocol": "17",
      "socket": "170229799"
    },
    {
      "address": "127.0.0.11",
      "path": "",
      "pid": "-1",
      "port": "45861",
      "protocol": "17",
      "socket": "170229799"
    }
  ]
}
